retention_reg.v
// ============================================================================
// Module: retention_reg.v
// Description: State Retention Power Gated (SRPG) Register Module
// Target Domain: Switchable Power Domain (PD_CPU)
// ============================================================================

module retention_reg #(
    parameter WIDTH = 32
)(
    input  wire             clk,           // Functional clock
    input  wire             rst_n,         // Functional reset
    input  wire             ret_save,      // Save active state into balloon latch
    input  wire             ret_restore,   // Restore state from balloon latch
    input  wire [WIDTH-1:0] d_in,          // Data input
    output reg  [WIDTH-1:0] q_out          // Data output
);

    // Internal "Balloon Latch" powered by VDD_AO (Always-On Supply)
    reg [WIDTH-1:0] shadow_latch;

    // 1. Normal Functional Register Update
    always @(posedge clk or negedge rst_n) begin
        if (!rst_n) begin
            q_out <= {WIDTH{1'b0}};
        end else begin
            q_out <= d_in;
        end
    end

    // 2. SRPG Shadow Latch Operations
    // - On ret_save: Snapshot current active state into shadow storage
    // - On ret_restore: Force shadow storage back into active register
    always @(*) begin
        if (ret_save) begin
            shadow_latch = q_out;
        end
    end

    always @(*) begin
        if (ret_restore) begin
            q_out = shadow_latch;
        end
    end

endmodule

isolation_wrapper.v
// ============================================================================
// Module: isolation_wrapper.v
// Description: Multi-bit Low-Power Output Isolation Cell
// Target Domain: Boundary between Power-Gated Domain and Always-On Domain
// ============================================================================

module isolation_wrapper #(
    parameter WIDTH = 32,
    parameter CLAMP_VALUE = 1'b0  // Clamps output to 0 (or 1) during isolation
)(
    input  wire [WIDTH-1:0] in_data,   // Signal coming from switchable power domain
    input  wire             iso_en,    // Isolation enable (1: active isolation)
    output wire [WIDTH-1:0] out_data   // Isolated output driven to rest of SoC
);

    // Structural clamp logic:
    // When iso_en == 1, outputs hold CLAMP_VALUE.
    // When iso_en == 0, outputs pass through in_data transparently.
    assign out_data = iso_en ? {WIDTH{CLAMP_VALUE}} : in_data;

endmodule

pmc_core.v
// ============================================================================
// Module: pmc_core.v
// Description: Multi-Domain SoC Power Management Controller (PMC) - Verilog-2001
// Target Domain: Manages sequencing for Power Domain PD_CPU
// ============================================================================

module pmc_core #(
    parameter TIMEOUT_CYCLES = 4  // Delay cycles for power switch/rail settling
)(
    input  wire clk_aon,          // Always-On Clock
    input  wire rst_n_aon,        // Always-On Reset (Active Low)

    // Handshake Interfaces (from System / CPU Core)
    input  wire sleep_req,        // Sleep request (e.g., from WFI logic)
    input  wire wake_irq,         // Wakeup interrupt signal
    output reg  pmc_idle,         // PMC idle / sleep state indicator

    // Power Domain Control Sideband Signals
    output reg  cpu_ret_save,     // 1: Save state to SRPG registers
    output reg  cpu_ret_restore,  // 1: Restore state from SRPG registers
    output reg  cpu_iso_en,       // 1: Clamp outputs to prevent X-prop
    output reg  cpu_rst_n,        // 0: Assert reset to domain
    output reg  cpu_pwr_sw_en     // 1: Turn ON power switch, 0: OFF
);

    // FSM State Definitions using Parameters
    parameter ST_ACTIVE      = 4'b0000;
    parameter ST_RET_SAVE    = 4'b0001;
    parameter ST_ISO_ENABLE  = 4'b0011;
    parameter ST_RST_ASSERT  = 4'b0010;
    parameter ST_PWR_OFF     = 4'b0110;
    parameter ST_SLEEP       = 4'b0111;
    parameter ST_PWR_ON      = 4'b0101;
    parameter ST_ISO_DISABLE = 4'b0100;
    parameter ST_RET_RESTORE = 4'b1100;
    parameter ST_RST_RELEASE = 4'b1000;

    reg [3:0] current_state, next_state;

    // Internal Counter for Power Rail Ramp Delays
    reg [3:0] timer;
    reg       timer_clear;

    // ------------------------------------------------------------------------
    // 1. FSM Sequential State Register & Delay Counter
    // ------------------------------------------------------------------------
    always @(posedge clk_aon or negedge rst_n_aon) begin
        if (!rst_n_aon) begin
            current_state <= ST_ACTIVE;
            timer         <= 4'b0000;
        end else begin
            current_state <= next_state;
            if (timer_clear)
                timer <= 4'b0000;
            else
                timer <= timer + 1'b1;
        end
    end

    // ------------------------------------------------------------------------
    // 2. FSM Next-State Logic
    // ------------------------------------------------------------------------
    always @(*) begin
        next_state  = current_state;
        timer_clear = 1'b0;

        case (current_state)
            ST_ACTIVE: begin
                if (sleep_req) begin
                    next_state  = ST_RET_SAVE;
                    timer_clear = 1'b1;
                end
            end

            ST_RET_SAVE: begin
                if (timer == TIMEOUT_CYCLES) begin
                    next_state  = ST_ISO_ENABLE;
                    timer_clear = 1'b1;
                end
            end

            ST_ISO_ENABLE: begin
                if (timer == TIMEOUT_CYCLES) begin
                    next_state  = ST_RST_ASSERT;
                    timer_clear = 1'b1;
                end
            end

            ST_RST_ASSERT: begin
                if (timer == TIMEOUT_CYCLES) begin
                    next_state  = ST_PWR_OFF;
                    timer_clear = 1'b1;
                end
            end

            ST_PWR_OFF: begin
                if (timer == TIMEOUT_CYCLES) begin
                    next_state  = ST_SLEEP;
                    timer_clear = 1'b1;
                end
            end

            ST_SLEEP: begin
                if (wake_irq) begin
                    next_state  = ST_PWR_ON;
                    timer_clear = 1'b1;
                end
            end

            ST_PWR_ON: begin
                if (timer == TIMEOUT_CYCLES) begin
                    next_state  = ST_ISO_DISABLE;
                    timer_clear = 1'b1;
                end
            end

            ST_ISO_DISABLE: begin
                if (timer == TIMEOUT_CYCLES) begin
                    next_state  = ST_RET_RESTORE;
                    timer_clear = 1'b1;
                end
            end

            ST_RET_RESTORE: begin
                if (timer == TIMEOUT_CYCLES) begin
                    next_state  = ST_RST_RELEASE;
                    timer_clear = 1'b1;
                end
            end

            ST_RST_RELEASE: begin
                if (timer == TIMEOUT_CYCLES) begin
                    next_state  = ST_ACTIVE;
                    timer_clear = 1'b1;
                end
            end

            default: next_state = ST_ACTIVE;
        endcase
    end

    // ------------------------------------------------------------------------
    // 3. Output Assignment Logic
    // ------------------------------------------------------------------------
    always @(*) begin
        // Safe Defaults
        cpu_ret_save    = 1'b0;
        cpu_ret_restore = 1'b0;
        cpu_iso_en      = 1'b0;
        cpu_rst_n       = 1'b1;
        cpu_pwr_sw_en   = 1'b1;
        pmc_idle        = 1'b0;

        case (current_state)
            ST_ACTIVE: begin
                // All active defaults
            end

            ST_RET_SAVE: begin
                cpu_ret_save = 1'b1;
            end

            ST_ISO_ENABLE: begin
                cpu_iso_en = 1'b1;
            end

            ST_RST_ASSERT: begin
                cpu_iso_en = 1'b1;
                cpu_rst_n  = 1'b0;
            end

            ST_PWR_OFF: begin
                cpu_iso_en    = 1'b1;
                cpu_rst_n     = 1'b0;
                cpu_pwr_sw_en = 1'b0;
            end

            ST_SLEEP: begin
                cpu_iso_en    = 1'b1;
                cpu_rst_n     = 1'b0;
                cpu_pwr_sw_en = 1'b0;
                pmc_idle      = 1'b1;
            end

            ST_PWR_ON: begin
                cpu_iso_en    = 1'b1;
                cpu_rst_n     = 1'b0;
                cpu_pwr_sw_en = 1'b1;
            end

            ST_ISO_DISABLE: begin
                cpu_iso_en  = 1'b0;
                cpu_rst_n   = 1'b0;
            end

            ST_RET_RESTORE: begin
                cpu_ret_restore = 1'b1;
                cpu_rst_n       = 1'b0;
            end

            ST_RST_RELEASE: begin
                cpu_rst_n = 1'b1;
            end
        endcase
    end

endmodule

tb/tb_pmc_core.v
// ============================================================================
// Module: tb_pmc_core.v
// Description: Testbench for Multi-Domain PMC and Isolation/Retention Logic
// ============================================================================

`timescale 1ns/1ps

module tb_pmc_core;

    // Clock and Reset
    reg clk_aon;
    reg rst_n_aon;

    // PMC Handshake Inputs
    reg sleep_req;
    reg wake_irq;

    // PMC Outputs
    wire pmc_idle;
    wire cpu_ret_save;
    wire cpu_ret_restore;
    wire cpu_iso_en;
    wire cpu_rst_n;
    wire cpu_pwr_sw_en;

    // Subsystem Signals to Test Isolation & Retention
    reg  [31:0] cpu_data_out;
    wire [31:0] isolated_data_out;
    reg  [31:0] reg_data_in;
    wire [31:0] reg_data_out;

    // ------------------------------------------------------------------------
    // 1. Instantiate Units Under Test (UUT)
    // ------------------------------------------------------------------------
    pmc_core #(
        .TIMEOUT_CYCLES(4)
    ) u_pmc_core (
        .clk_aon        (clk_aon),
        .rst_n_aon      (rst_n_aon),
        .sleep_req      (sleep_req),
        .wake_irq       (wake_irq),
        .pmc_idle       (pmc_idle),
        .cpu_ret_save   (cpu_ret_save),
        .cpu_ret_restore(cpu_ret_restore),
        .cpu_iso_en     (cpu_iso_en),
        .cpu_rst_n      (cpu_rst_n),
        .cpu_pwr_sw_en  (cpu_pwr_sw_en)
    );

    // Isolation Wrapper Instance
    isolation_wrapper #(
        .WIDTH(32),
        .CLAMP_VALUE(1'b0)
    ) u_iso_wrapper (
        .in_data (cpu_data_out),
        .iso_en  (cpu_iso_en),
        .out_data(isolated_data_out)
    );

    // Retention Register Instance
    retention_reg #(
        .WIDTH(32)
    ) u_ret_reg (
        .clk        (clk_aon),
        .rst_n      (cpu_rst_n),
        .ret_save   (cpu_ret_save),
        .ret_restore(cpu_ret_restore),
        .d_in       (reg_data_in),
        .q_out      (reg_data_out)
    );

    // ------------------------------------------------------------------------
    // 2. Clock Generation (100MHz Always-On Clock)
    // ------------------------------------------------------------------------
    always #5 clk_aon = ~clk_aon;

    // ------------------------------------------------------------------------
    // 3. Test Stimulus and Sequence Verification
    // ------------------------------------------------------------------------
    initial begin
        // Dump VCD file for GTKWave visualization
        $dumpfile("sim/pmc_sim.vcd");
        $dumpvars(0, tb_pmc_core);

        // Initialize Signals
        clk_aon      = 0;
        rst_n_aon    = 0;
        sleep_req    = 0;
        wake_irq     = 0;
        cpu_data_out = 32'hDEADBEEF;
        reg_data_in  = 32'h12345678;

        $display("--------------------------------------------------");
        $display("[TB] Starting Power-Aware PMC Simulation...");
        $display("--------------------------------------------------");

        // Release Power-On Reset
        #20 rst_n_aon = 1;
        #20;

        // --- STEP A: Trigger Sleep Sequence ---
        $display("[TB] @ %0nt: Driving SLEEP_REQ", $time);
        sleep_req = 1;

        // Wait until power switch is completely turned off
        wait(cpu_pwr_sw_en == 0);
        $display("[TB] @ %0nt: Power Switch is OFF. Corrupting CPU Domain Outputs to 'X'...", $time);
        cpu_data_out = 32'hXXXXXXXX; // Simulate power-gated unpowered bus floating

        // Verify isolation is holding clamp value 0
        #10;
        if (isolated_data_out === 32'h00000000) begin
            $display("[SUCCESS] Isolation logic active! Unpowered 'X' signals blocked.");
        end else begin
            $display("[ERROR] Isolation failed! Leakage detected: %h", isolated_data_out);
        end

        // --- STEP B: Trigger Wakeup Sequence ---
        #100;
        $display("[TB] @ %0nt: Driving WAKE_IRQ Interrupt", $time);
        sleep_req = 0;
        wake_irq  = 1;

        // Wait until system restores state and releases reset
        wait(cpu_rst_n == 1);
        wake_irq     = 0;
        cpu_data_out = 32'hCAFEFEED; // Restore CPU active outputs

        #40;
        $display("[TB] @ %0nt: Checking Retention Register Value: %h", $time, reg_data_out);
        if (reg_data_out === 32'h12345678) begin
            $display("[SUCCESS] Retention Register context accurately restored!");
        end else begin
            $display("[ERROR] Retention state corrupted: %h", reg_data_out);
        end

        $display("--------------------------------------------------");
        $display("[TB] Simulation Completed Successfully!");
        $display("--------------------------------------------------");
        $finish;
    end

endmodule

sim/pmc_sim.vcd
$date
	Wed Oct 07 17:25:27 2026
$end
$version
	Icarus Verilog
$end
$timescale
	1ps
$end
$scope module tb_pmc_core $end
$var wire 32 ! reg_data_out [31:0] $end
$var wire 1 " pmc_idle $end
$var wire 32 # isolated_data_out [31:0] $end
$var wire 1 $ cpu_rst_n $end
$var wire 1 % cpu_ret_save $end
$var wire 1 & cpu_ret_restore $end
$var wire 1 ' cpu_pwr_sw_en $end
$var wire 1 ( cpu_iso_en $end
$var reg 1 ) clk_aon $end
$var reg 32 * cpu_data_out [31:0] $end
$var reg 32 + reg_data_in [31:0] $end
$var reg 1 , rst_n_aon $end
$var reg 1 - sleep_req $end
$var reg 1 . wake_irq $end
$scope module u_iso_wrapper $end
$var wire 32 / in_data [31:0] $end
$var wire 32 0 out_data [31:0] $end
$var wire 1 ( iso_en $end
$upscope $end
$scope module u_pmc_core $end
$var wire 1 ) clk_aon $end
$var wire 1 , rst_n_aon $end
$var wire 1 - sleep_req $end
$var wire 1 . wake_irq $end
$var reg 1 ( cpu_iso_en $end
$var reg 1 ' cpu_pwr_sw_en $end
$var reg 1 & cpu_ret_restore $end
$var reg 1 % cpu_ret_save $end
$var reg 1 $ cpu_rst_n $end
$var reg 4 1 current_state [3:0] $end
$var reg 4 2 next_state [3:0] $end
$var reg 1 " pmc_idle $end
$var reg 4 3 timer [3:0] $end
$var reg 1 4 timer_clear $end
$upscope $end
$scope module u_ret_reg $end
$var wire 1 ) clk $end
$var wire 32 5 d_in [31:0] $end
$var wire 1 & ret_restore $end
$var wire 1 % ret_save $end
$var wire 1 $ rst_n $end
$var reg 32 6 q_out [31:0] $end
$var reg 32 7 shadow_latch [31:0] $end
$upscope $end
$upscope $end
$enddefinitions $end
#0
$dumpvars
bx 7
bx 6
b10010001101000101011001111000 5
04
b0 3
b0 2
b0 1
b11011110101011011011111011101111 0
b11011110101011011011111011101111 /
0.
0-
0,
b10010001101000101011001111000 +
b11011110101011011011111011101111 *
0)
0(
1'
0&
0%
1$
b11011110101011011011111011101111 #
0"
bx !
$end
#5000
b10010001101000101011001111000 !
b10010001101000101011001111000 6
1)
#10000
0)
#15000
1)
#20000
0)
1,
#25000
b1 3
1)
#30000
0)
#35000
b10 3
1)
#40000
14
b1 2
0)
1-
#45000
b10010001101000101011001111000 7
1%
04
b0 3
b1 1
1)
#50000
0)
#55000
b1 3
1)
#60000
0)
#65000
b10 3
1)
#70000
0)
#75000
b11 3
1)
#80000
0)
#85000
14
b11 2
b100 3
1)
#90000
0)
#95000
b0 #
b0 0
1(
0%
04
b0 3
b11 1
1)
#100000
0)
#105000
b1 3
1)
#110000
0)
#115000
b10 3
1)
#120000
0)
#125000
b11 3
1)
#130000
0)
#135000
14
b10 2
b100 3
1)
#140000
0)
#145000
b0 !
b0 6
0$
1(
04
b0 3
b10 1
1)
#150000
0)
#155000
b1 3
1)
#160000
0)
#165000
b10 3
1)
#170000
0)
#175000
b11 3
1)
#180000
0)
#185000
14
b110 2
b100 3
1)
#190000
0)
#195000
bx *
bx /
0'
0$
1(
04
b0 3
b110 1
1)
#200000
0)
#205000
b1 3
1)
#210000
0)
#215000
b10 3
1)
#220000
0)
#225000
b11 3
1)
#230000
0)
#235000
14
b111 2
b100 3
1)
#240000
0)
#245000
1"
0'
0$
1(
04
b0 3
b111 1
1)
#250000
0)
#255000
b1 3
1)
#260000
0)
#265000
b10 3
1)
#270000
0)
#275000
b11 3
1)
#280000
0)
#285000
b100 3
1)
#290000
0)
#295000
b101 3
1)
#300000
0)
#305000
0"
1'
0$
1(
b0 3
b101 1
04
b101 2
1)
1.
0-
#310000
0)
#315000
b1 3
1)
#320000
0)
#325000
b10 3
1)
#330000
0)
#335000
b11 3
1)
#340000
0)
#345000
14
b100 2
b100 3
1)
#350000
0)
#355000
bx #
bx 0
0$
0(
04
b0 3
b100 1
1)
#360000
0)
#365000
b1 3
1)
#370000
0)
#375000
b10 3
1)
#380000
0)
#385000
b11 3
1)
#390000
0)
#395000
14
b1100 2
b100 3
1)
#400000
0)
#405000
b0 !
b0 6
1&
0$
04
b0 3
b1100 1
1)
#410000
0)
#415000
b1 3
1)
#420000
0)
#425000
b10 3
1)
#430000
0)
#435000
b11 3
1)
#440000
0)
#445000
14
b1000 2
b100 3
1)
#450000
0)
#455000
b11001010111111101111111011101101 #
b11001010111111101111111011101101 0
b11001010111111101111111011101101 *
b11001010111111101111111011101101 /
0.
1$
0&
04
b0 3
b1000 1
1)
#460000
0)
#465000
b1 3
b10010001101000101011001111000 !
b10010001101000101011001111000 6
1)
#470000
0)
#475000
b10 3
1)
#480000
0)
#485000
b11 3
1)
#490000
0)
#495000
14
b0 2
b100 3
1)
